setup.py
cs_prob/Binomialdistribution.py
cs_prob/Gaussiandistribution.py
cs_prob/Generaldistribution.py
cs_prob/__init__.py
cs_prob/example_code.py
cs_prob.egg-info/PKG-INFO
cs_prob.egg-info/SOURCES.txt
cs_prob.egg-info/dependency_links.txt
cs_prob.egg-info/not-zip-safe
cs_prob.egg-info/top_level.txt