Metadata-Version: 1.0
Name: cs-prob
Version: 0.1
Summary: Probability distributions
Home-page: UNKNOWN
Author: Carlos Sell
Author-email: UNKNOWN
License: UNKNOWN
Platform: UNKNOWN
